tdmrsdm/__init__.py
tdmrsdm/core.py
tdmrsdm/constants/td_mrsdm_constants_v2019.json
tdmrsdm/constants/td_mrsdm_constants_v2019_optimized_v1.json
tdmrsdm/constants/td_mrsdm_constants_v2019_optimized_v2.json
tdmrsdm-2025.7.3.dist-info/licenses/LICENSE
tdmrsdm-2025.7.3.dist-info/METADATA
tdmrsdm-2025.7.3.dist-info/WHEEL
tdmrsdm-2025.7.3.dist-info/top_level.txt
tdmrsdm-2025.7.3.dist-info/RECORD
