Metadata-Version: 2.4
Name: tdmrsdm
Version: 2025.7.3
Summary: A Temperature-Dependent Multi-Relaxation Spectroscopic Dielectric Model (TD-MRSDM).
Author-email: Morteza Khazaei <morteza.khazaei@usherbrooke.ca>
License: MIT License
Project-URL: Homepage, https://github.com/Morteza-Khazaei/TD-MRSDM
Project-URL: Repository, https://github.com/Morteza-Khazaei/TD-MRSDM
Classifier: Programming Language :: Python :: 3
Classifier: Programming Language :: Python :: 3.7
Classifier: Programming Language :: Python :: 3.8
Classifier: Programming Language :: Python :: 3.9
Classifier: License :: OSI Approved :: MIT License
Classifier: Operating System :: OS Independent
Requires-Python: >=3.7
License-File: LICENSE
Requires-Dist: matplotlib
Requires-Dist: seaborn
Requires-Dist: numpy
Dynamic: license-file
